xop/__init__.py
xop/contrib/__init__.py
xop/contrib/zeep.py
xop/datatypes.py
xop/processors/__init__.py
xop/processors/soap_ui_style.py
xop/serialization/__init__.py
xop/serialization/mime.py
xop-0.2.0.dist-info/WHEEL
xop-0.2.0.dist-info/METADATA
xop-0.2.0.dist-info/RECORD
